{
  "kind": "collectionType",
  "collectionName": "videos",
  "info": {
    "name": "video",
    "description": ""
  },
  "options": {
    "increments": true,
    "timestamps": true,
    "draftAndPublish": false
  },
  "attributes": {
    "title": {
      "type": "string"
    },
    "previewImage": {
      "model": "file",
      "via": "related",
      "allowedTypes": [
        "images",
        "files",
        "videos"
      ],
      "plugin": "upload",
      "required": false
    },
    "category": {
      "type": "string"
    },
    "video": {
      "model": "file",
      "via": "related",
      "allowedTypes": [
        "images",
        "files",
        "videos"
      ],
      "plugin": "upload",
      "required": false
    }
  }
}
